cfdn/__init__.py
cfdn/preprocess.py
cfdn/utils.py
cfdn/version.py
cftools/__init__.py
cftools/preprocess.py
cftools/utils.py
cftools/version.py
cfdn-0.1.dev0.dist-info/LICENSE
cfdn-0.1.dev0.dist-info/METADATA
cfdn-0.1.dev0.dist-info/WHEEL
cfdn-0.1.dev0.dist-info/top_level.txt
cfdn-0.1.dev0.dist-info/RECORD
