Metadata-Version: 2.1
Name: cfdn
Version: 0.1.dev0
Summary: cfdn: Implementation and visualization of divisive normalization connective fields
Home-page: https://github.com/RonvdKlundert/cfdn/
Download-URL: https://github.com/RonvdKlundert/cfdn/archive/refs/tags/v0.1.dev-alpha.tar.gz
Author: RonvdKlundert
Author-email: klundertclan@hotmail.com
Maintainer: RonvdKlundert
Maintainer-email: klundertclan@hotmail.com
License: MIT
Platform: OS Independent
Classifier: Development Status :: 3 - Alpha
Classifier: Environment :: Console
Classifier: Intended Audience :: Science/Research
Classifier: License :: OSI Approved :: MIT License
Classifier: Operating System :: OS Independent
Classifier: Programming Language :: Python
Classifier: Topic :: Scientific/Engineering
License-File: LICENSE
